aiomcrcon/__init__.py
aiomcrcon/client.py
aiomcrcon/errors.py
aio_mc_rcon-3.4.1.dist-info/LICENSE
aio_mc_rcon-3.4.1.dist-info/METADATA
aio_mc_rcon-3.4.1.dist-info/WHEEL
aio_mc_rcon-3.4.1.dist-info/RECORD
