Metadata-Version: 2.3
Name: aio-mc-rcon
Version: 3.4.1
Summary: An async library for utilizing remote console on Minecraft Java Edition servers
License: MIT
Keywords: rcon,mcrcon,async,remote console,minecraft
Author: Milo Weinberg
Author-email: iapetus011@gmail.com
Requires-Python: >=3.9,<4.0
Classifier: License :: OSI Approved :: MIT License
Classifier: Programming Language :: Python :: 3
Classifier: Programming Language :: Python :: 3.9
Classifier: Programming Language :: Python :: 3.10
Classifier: Programming Language :: Python :: 3.11
Classifier: Programming Language :: Python :: 3.12
Classifier: Programming Language :: Python :: 3.13
Project-URL: Repository, https://github.com/Iapetus-11/aio-mc-rcon
